odoo/addons/partner_deduplicate_by_website/README.rst
odoo/addons/partner_deduplicate_by_website/__init__.py
odoo/addons/partner_deduplicate_by_website/__manifest__.py
odoo/addons/partner_deduplicate_by_website/i18n/ar.po
odoo/addons/partner_deduplicate_by_website/i18n/bg.po
odoo/addons/partner_deduplicate_by_website/i18n/bs.po
odoo/addons/partner_deduplicate_by_website/i18n/ca.po
odoo/addons/partner_deduplicate_by_website/i18n/crm_deduplicate_by_website.pot
odoo/addons/partner_deduplicate_by_website/i18n/cs.po
odoo/addons/partner_deduplicate_by_website/i18n/da.po
odoo/addons/partner_deduplicate_by_website/i18n/de.po
odoo/addons/partner_deduplicate_by_website/i18n/el_GR.po
odoo/addons/partner_deduplicate_by_website/i18n/en_GB.po
odoo/addons/partner_deduplicate_by_website/i18n/es.po
odoo/addons/partner_deduplicate_by_website/i18n/es_AR.po
odoo/addons/partner_deduplicate_by_website/i18n/es_CL.po
odoo/addons/partner_deduplicate_by_website/i18n/es_CO.po
odoo/addons/partner_deduplicate_by_website/i18n/es_CR.po
odoo/addons/partner_deduplicate_by_website/i18n/es_DO.po
odoo/addons/partner_deduplicate_by_website/i18n/es_EC.po
odoo/addons/partner_deduplicate_by_website/i18n/es_MX.po
odoo/addons/partner_deduplicate_by_website/i18n/es_PE.po
odoo/addons/partner_deduplicate_by_website/i18n/et.po
odoo/addons/partner_deduplicate_by_website/i18n/eu.po
odoo/addons/partner_deduplicate_by_website/i18n/fa.po
odoo/addons/partner_deduplicate_by_website/i18n/fi.po
odoo/addons/partner_deduplicate_by_website/i18n/fr.po
odoo/addons/partner_deduplicate_by_website/i18n/gl.po
odoo/addons/partner_deduplicate_by_website/i18n/he.po
odoo/addons/partner_deduplicate_by_website/i18n/hr.po
odoo/addons/partner_deduplicate_by_website/i18n/hr_HR.po
odoo/addons/partner_deduplicate_by_website/i18n/hu.po
odoo/addons/partner_deduplicate_by_website/i18n/id.po
odoo/addons/partner_deduplicate_by_website/i18n/it.po
odoo/addons/partner_deduplicate_by_website/i18n/ja.po
odoo_addon_partner_deduplicate_by_website-18.0.1.0.0.2.dist-info/METADATA
odoo_addon_partner_deduplicate_by_website-18.0.1.0.0.2.dist-info/WHEEL
odoo_addon_partner_deduplicate_by_website-18.0.1.0.0.2.dist-info/top_level.txt
odoo_addon_partner_deduplicate_by_website-18.0.1.0.0.2.dist-info/RECORD
